google/cloud/artifactregistry/__init__.py
google/cloud/artifactregistry/gapic_version.py
google/cloud/artifactregistry/py.typed
google/cloud/artifactregistry_v1/__init__.py
google/cloud/artifactregistry_v1/gapic_metadata.json
google/cloud/artifactregistry_v1/gapic_version.py
google/cloud/artifactregistry_v1/py.typed
google/cloud/artifactregistry_v1/services/__init__.py
google/cloud/artifactregistry_v1/services/artifact_registry/__init__.py
google/cloud/artifactregistry_v1/services/artifact_registry/async_client.py
google/cloud/artifactregistry_v1/services/artifact_registry/client.py
google/cloud/artifactregistry_v1/services/artifact_registry/pagers.py
google/cloud/artifactregistry_v1/services/artifact_registry/transports/__init__.py
google/cloud/artifactregistry_v1/services/artifact_registry/transports/base.py
google/cloud/artifactregistry_v1/services/artifact_registry/transports/grpc.py
google/cloud/artifactregistry_v1/services/artifact_registry/transports/grpc_asyncio.py
google/cloud/artifactregistry_v1/services/artifact_registry/transports/rest.py
google/cloud/artifactregistry_v1/services/artifact_registry/transports/rest_base.py
google/cloud/artifactregistry_v1/types/__init__.py
google/cloud/artifactregistry_v1/types/apt_artifact.py
google/cloud/artifactregistry_v1/types/artifact.py
google/cloud/artifactregistry_v1/types/attachment.py
google/cloud/artifactregistry_v1/types/export.py
google/cloud/artifactregistry_v1/types/file.py
google/cloud/artifactregistry_v1/types/generic.py
google/cloud/artifactregistry_v1/types/go.py
google/cloud/artifactregistry_v1/types/kfp_artifact.py
google/cloud/artifactregistry_v1/types/package.py
google/cloud/artifactregistry_v1/types/repository.py
google/cloud/artifactregistry_v1/types/rule.py
google/cloud/artifactregistry_v1/types/service.py
google/cloud/artifactregistry_v1/types/settings.py
google/cloud/artifactregistry_v1/types/tag.py
google/cloud/artifactregistry_v1/types/version.py
google_cloud_artifact_registry-1.19.0.dist-info/licenses/LICENSE
google_cloud_artifact_registry-1.19.0.dist-info/METADATA
google_cloud_artifact_registry-1.19.0.dist-info/WHEEL
google_cloud_artifact_registry-1.19.0.dist-info/top_level.txt
google_cloud_artifact_registry-1.19.0.dist-info/RECORD
